netfoll_tl/__init__.py
netfoll_tl/custom.py
netfoll_tl/functions.py
netfoll_tl/helpers.py
netfoll_tl/hints.py
netfoll_tl/password.py
netfoll_tl/requestiter.py
netfoll_tl/sync.py
netfoll_tl/types.py
netfoll_tl/utils.py
netfoll_tl/version.py
netfoll_tl/_updates/__init__.py
netfoll_tl/_updates/entitycache.py
netfoll_tl/_updates/messagebox.py
netfoll_tl/_updates/session.py
netfoll_tl/client/__init__.py
netfoll_tl/client/account.py
netfoll_tl/client/auth.py
netfoll_tl/client/bots.py
netfoll_tl/client/buttons.py
netfoll_tl/client/chats.py
netfoll_tl/client/dialogs.py
netfoll_tl/client/downloads.py
netfoll_tl/client/messageparse.py
netfoll_tl/client/messages.py
netfoll_tl/client/telegrambaseclient.py
netfoll_tl/client/telegramclient.py
netfoll_tl/client/updates.py
netfoll_tl/client/uploads.py
netfoll_tl/client/users.py
netfoll_tl/crypto/__init__.py
netfoll_tl/crypto/aes.py
netfoll_tl/crypto/aesctr.py
netfoll_tl/crypto/authkey.py
netfoll_tl/crypto/cdndecrypter.py
netfoll_tl/crypto/factorization.py
netfoll_tl/crypto/libssl.py
netfoll_tl/crypto/rsa.py
netfoll_tl/errors/__init__.py
netfoll_tl/errors/common.py
netfoll_tl/errors/rpcbaseerrors.py
netfoll_tl/errors/rpcerrorlist.py
netfoll_tl/events/__init__.py
netfoll_tl/events/album.py
netfoll_tl/events/callbackquery.py
netfoll_tl/events/chataction.py
netfoll_tl/events/common.py
netfoll_tl/events/inlinequery.py
netfoll_tl/events/messagedeleted.py
netfoll_tl/events/messageedited.py
netfoll_tl/events/messageread.py
netfoll_tl/events/newmessage.py
netfoll_tl/events/raw.py
netfoll_tl/events/userupdate.py
netfoll_tl/extensions/__init__.py
netfoll_tl/extensions/binaryreader.py
netfoll_tl/extensions/html.py
netfoll_tl/extensions/markdown.py
netfoll_tl/extensions/messagepacker.py
netfoll_tl/network/__init__.py
netfoll_tl/network/authenticator.py
netfoll_tl/network/mtprotoplainsender.py
netfoll_tl/network/mtprotosender.py
netfoll_tl/network/mtprotostate.py
netfoll_tl/network/requeststate.py
netfoll_tl/network/connection/__init__.py
Netfoll_TL-2.0.1.dist-info/LICENSE
Netfoll_TL-2.0.1.dist-info/METADATA
Netfoll_TL-2.0.1.dist-info/WHEEL
Netfoll_TL-2.0.1.dist-info/top_level.txt
Netfoll_TL-2.0.1.dist-info/RECORD
