Metadata-Version: 2.1
Name: Netfoll-TL
Version: 2.0.1
Summary: Modified Telethon
Home-page: https://github.com/Netfoll/Netfoll-TL
Download-URL: https://github.com/Netfoll/Netfoll-TL/releases
Author: ASNCT
License: MIT
Keywords: telegram api chat client library messaging mtproto netfoll telethon tl
Classifier: Development Status :: 5 - Production/Stable
Classifier: Intended Audience :: Developers
Classifier: Topic :: Communications :: Chat
Classifier: License :: OSI Approved :: MIT License
Classifier: Programming Language :: Python :: 3
Classifier: Programming Language :: Python :: 3.5
Classifier: Programming Language :: Python :: 3.6
Classifier: Programming Language :: Python :: 3.7
Classifier: Programming Language :: Python :: 3.8
Requires-Python: >=3.5
License-File: LICENSE
Requires-Dist: pyaes
Requires-Dist: rsa
Provides-Extra: cryptg
Requires-Dist: cryptg ; extra == 'cryptg'
